struct_mcp/__init__.py
struct_mcp/__main__.py
struct_mcp/cli.py
struct_mcp/mcp_server.py
struct_mcp/struct_parser.py
struct_mcp/converters/__init__.py
struct_mcp/converters/avro.py
struct_mcp/converters/opensearch.py
struct_mcp/converters/protobuf.py
struct_mcp/converters/pydantic.py
struct_mcp/parsers/__init__.py
struct_mcp/parsers/avro_parser.py
struct_mcp/parsers/json_schema_parser.py
struct_mcp/parsers/opensearch_parser.py
struct_mcp/parsers/protobuf_parser.py
struct_mcp/parsers/pydantic_parser.py
struct_mcp/parsers/yaml_parser.py
struct_mcp-0.1.0.dist-info/METADATA
struct_mcp-0.1.0.dist-info/WHEEL
struct_mcp-0.1.0.dist-info/entry_points.txt
struct_mcp-0.1.0.dist-info/licenses/LICENSE
struct_mcp-0.1.0.dist-info/RECORD
