Metadata-Version: 2.4
Name: struct-mcp
Version: 0.1.0
Summary: Transform data structure definitions into queryable MCP servers
Project-URL: Homepage, https://github.com/LaurEars/struct-mcp
Project-URL: Repository, https://github.com/LaurEars/struct-mcp
Project-URL: Issues, https://github.com/LaurEars/struct-mcp/issues
Project-URL: Documentation, https://github.com/LaurEars/struct-mcp#readme
Author: Laura Rupprecht
License: MIT License
License-File: LICENSE
Keywords: ai,data-structures,mcp,query,schema,yaml
Classifier: Development Status :: 3 - Alpha
Classifier: Intended Audience :: Developers
Classifier: License :: OSI Approved :: MIT License
Classifier: Programming Language :: Python :: 3
Classifier: Programming Language :: Python :: 3.10
Classifier: Programming Language :: Python :: 3.11
Classifier: Programming Language :: Python :: 3.12
Classifier: Programming Language :: Python :: 3.13
Classifier: Topic :: Communications
Classifier: Topic :: Database
Classifier: Topic :: Scientific/Engineering :: Artificial Intelligence
Classifier: Topic :: Scientific/Engineering :: Information Analysis
Classifier: Topic :: Software Development :: Libraries :: Python Modules
Requires-Python: >=3.10
Requires-Dist: mcp>=1.0.0
Requires-Dist: pydantic>=2.0.0
Requires-Dist: pyyaml>=6.0.0
Provides-Extra: converters
Requires-Dist: avro>=1.11.0; extra == 'converters'
Requires-Dist: elasticsearch>=8.0.0; extra == 'converters'
Provides-Extra: dev
Requires-Dist: pytest-asyncio>=0.21.0; extra == 'dev'
Requires-Dist: pytest-cov>=4.0.0; extra == 'dev'
Requires-Dist: pytest>=7.0.0; extra == 'dev'
